{
	"class": ["navigation"],
	"properties": {
		"text": "College University",
		"color": "#003b71"
	},
	"entities": [
		{
			"class": ["image"],
			"properties": {
				"alt": "My Home"
			},
			"links": [
				{
					"rel": ["alternate"],
					"href": "assets/logo.png"
				},
				{
					"rel": ["/rel/home"],
					"href": "/home/"
				}
			]
		},
		{
			"class": ["item", "link"],
			"properties": {
				"text": "Calendar"
			},
			"links": [
				{
					"rel": ["self"],
					"href": "/d2l/le/calendar/6606"
				}
			]
		},
		{
			"class": ["item", "link"],
			"properties": {
				"text": "Checklist"
			},
			"links": [
				{
					"rel": ["self"],
					"href": "/d2l/lms/checklist/checklists.d2l?ou=6606"
				}
			]
		},
		{
			"class": ["item", "link"],
			"properties": {
				"text": "Content"
			},
			"links": [
				{
					"rel": ["self"],
					"href": "/d2l/le/content/6609/Home"
				}
			]
		},
		{
			"class": ["item", "link"],
			"properties": {
				"text": "Discussions"
			},
			"links": [
				{
					"rel": ["self"],
					"href": "/d2l/le/6606/discussions/List"
				}
			]
		},
		{
			"class": ["item", "link"],
			"properties": {
				"text": "Assignments"
			},
			"links": [
				{
					"rel": ["self"],
					"href": "/d2l/lms/dropbox/dropbox.d2l?ou=6606"
				}
			]
		},
		{
			"class": ["item", "group"],
			"properties": {
				"text": "Menu"
			},
			"entities": [
				{
					"class": ["item", "link"],
					"properties": {
						"text": "Announcements"
					},
					"links": [
						{
							"rel": ["self"],
							"href": "/d2l/lms/news/main.d2l?ou=6606"
						}
					]
				},
				{
					"class": ["item", "link"],
					"properties": {
						"text": "Quizzes"
					},
					"links": [
						{
							"rel": ["self"],
							"href": "/d2l/lms/quizzing/admin/quizzes_manage.d2l?ou=6606"
						}
					]
				}
			]
		}
	],
	"links": [
		{
			"rel": ["self"],
			"href": "/api/hm/navigation/6606"
		}
	]
}
